utils/__init__.py
utils/database.py
utils/logging.py
utils/proxy.py
utils/scraper.py
newspapers3k_scraper-1.0.0.dist-info/METADATA
newspapers3k_scraper-1.0.0.dist-info/WHEEL
newspapers3k_scraper-1.0.0.dist-info/top_level.txt
newspapers3k_scraper-1.0.0.dist-info/RECORD
